{
  "appPageId" : "8f5deafd-d45c-481f-a633-1c52c313d9d1",
  "componentName" : "siteforce:sldsOneColLayout",
  "dataProviders" : [ ],
  "id" : "44ca21da-f16f-4ce3-b76d-6c8bca16b1f3",
  "label" : "Forgot Password",
  "regions" : [ {
    "components" : [ {
      "componentAttributes" : {
        "richTextValue" : "<div style=\"text-align: center;\"><span style=\"font-size:22px\">PASSWORD RESET</span></div>"
      },
      "componentName" : "forceCommunity:richTextInline",
      "id" : "f84b05d2-cff1-487e-bfa4-92cec5a19466",
      "renderPriority" : "NEUTRAL",
      "renditionMap" : { },
      "type" : "component"
    }, {
      "componentAttributes" : {
        "richTextValue" : "<div style=\"text-align: center;\">To reset your password, we'll need your username.<br/> We'll send password reset instructions to the email address associated with your account.</div>"
      },
      "componentName" : "forceCommunity:richTextInline",
      "id" : "1f60f01f-81f7-4769-94de-6a62fd838c52",
      "renderPriority" : "NEUTRAL",
      "renditionMap" : { },
      "type" : "component"
    }, {
      "componentAttributes" : {
        "checkEmailUrl" : "./CheckPasswordResetEmail",
        "submitButtonLabel" : "Reset Password",
        "usernameLabel" : "Username"
      },
      "componentName" : "salesforceIdentity:forgotPassword2",
      "id" : "9d9e7502-4b2d-4bf2-bd33-ca39c14f24a8",
      "renderPriority" : "NEUTRAL",
      "renditionMap" : { },
      "type" : "component"
    }, {
      "componentAttributes" : {
        "richTextValue" : "<div style=\"text-align: center;\"><a href=\"./\">Cancel</a></div>"
      },
      "componentName" : "forceCommunity:richTextInline",
      "id" : "51362157-f9f7-4645-90c6-00598d6a8291",
      "renderPriority" : "NEUTRAL",
      "renditionMap" : { },
      "type" : "component"
    } ],
    "id" : "1154c5e8-1f7d-40eb-bd24-700f94ded700",
    "regionName" : "content",
    "type" : "region"
  }, {
    "components" : [ {
      "componentAttributes" : {
        "customHeadTags" : "",
        "description" : "",
        "title" : "Forgot Password"
      },
      "componentName" : "forceCommunity:seoAssistant",
      "id" : "bca93c34-7e16-4cfd-83fc-22eb9ed20a07",
      "renditionMap" : { },
      "type" : "component"
    } ],
    "id" : "7808912c-8d2d-4894-a572-fcb7ab0d4920",
    "regionName" : "sfdcHiddenRegion",
    "type" : "region"
  } ],
  "themeLayoutType" : "Login",
  "type" : "view",
  "viewType" : "forgot-password"
}